README.md
setup.py
test/test.py
tkitMarkerFast/MarkerFast.py
tkitMarkerFast/__init__.py
tkitMarkerFast.egg-info/PKG-INFO
tkitMarkerFast.egg-info/SOURCES.txt
tkitMarkerFast.egg-info/dependency_links.txt
tkitMarkerFast.egg-info/requires.txt
tkitMarkerFast.egg-info/top_level.txt