Metadata-Version: 2.1
Name: tkitMarkerFast
Version: 0.0.0.1
Summary: Terry toolkit tkitMarkerFast
Home-page: https://github.com/napoler/tkitMarkerFast
Author: Terry Chan
Author-email: napoler2008@gmail.com
License: UNKNOWN
Platform: UNKNOWN
